rakan/GameCostants.py
rakan/Globals.py
rakan/LowLevelErrors.py
rakan/Rakan.py
rakan/Xayah.py
rakan/__init__.py
rakan/py.typed
rakan-0.0.10.dist-info/LICENSE
rakan-0.0.10.dist-info/METADATA
rakan-0.0.10.dist-info/WHEEL
rakan-0.0.10.dist-info/top_level.txt
rakan-0.0.10.dist-info/RECORD
